iotanalyzer.py
iotanalyzer-0.0.1.dist-info/LICENSE
iotanalyzer-0.0.1.dist-info/METADATA
iotanalyzer-0.0.1.dist-info/WHEEL
iotanalyzer-0.0.1.dist-info/top_level.txt
iotanalyzer-0.0.1.dist-info/RECORD
